<Properties GitUserInfo="UsingMD" StartupConfiguration="{D61B2A6B-04A7-450A-BC81-3CCD898EEDBC}|Default">
  <MonoDevelop.Ide.ItemProperties.OurSpace PreferredExecutionTarget="/Applications/Google Chrome.app" />
  <MonoDevelop.Ide.Workspace ActiveConfiguration="Debug" />
  <MonoDevelop.Ide.Workbench ActiveDocument="OurSpace/Views/Dashboard/Index.cshtml">
    <Files>
      <File FileName="OurSpace/Views/About/Index.cshtml" />
      <File FileName="OurSpace/Views/Home/Index.cshtml" />
      <File FileName="OurSpace/Views/hubs/homeroom.cshtml" />
      <File FileName="OurSpace/Views/hubs/Index.cshtml" />
      <File FileName="OurSpace/Views/hubs/macao.cshtml" />
      <File FileName="OurSpace/Views/hubs/plugit.cshtml" />
      <File FileName="OurSpace/Views/hubs/space.cshtml" />
      <File FileName="OurSpace/Views/hubs/stream.cshtml" />
      <File FileName="OurSpace/Models/Bookings.cs" Line="17" Column="45" />
      <File FileName="OurSpace/Controllers/HomeController.cs" />
      <File FileName="OurSpace/Views/Shared/_Layout.cshtml" />
      <File FileName="OurSpace/Controllers/EmailController.cs" />
      <File FileName="OurSpace/Controllers/About.cs" />
      <File FileName="OurSpace/Program.cs" />
      <File FileName="OurSpace/appsettings.Development.json" />
      <File FileName="OurSpace/appsettings.json" />
      <File FileName="OurSpace/Views/Dashboard/Index.cshtml" Line="3" Column="4" />
      <File FileName="OurSpace/Views/Modals/modals.cshtml" />
      <File FileName="OurSpace/Controllers/DashboardController.cs" />
      <File FileName="OurSpace/Controllers/HubsController.cs" />
      <File FileName="../../../../usr/local/share/dotnet/sdk/7.0.311/Sdks/Microsoft.NET.Sdk/targets/Microsoft.PackageDependencyResolution.targets" />
      <File FileName="OurSpace/Views/Home/login.cshtml" />
      <File FileName="OurSpace/Models/Accepted.cs" Line="9" Column="1" />
      <File FileName="OurSpace/Database/AddDbContext.cs" />
      <File FileName="OurSpace/Models/Enumerables.cs" Line="6" Column="27" />
    </Files>
    <Pads>
      <Pad Id="ProjectPad">
        <State name="__root__">
          <Node name="OurSpace" expanded="True">
            <Node name="OurSpace" expanded="True">
              <Node name="Models" expanded="True" />
              <Node name="Views" expanded="True">
                <Node name="About" expanded="True" />
                <Node name="Dashboard" expanded="True">
                  <Node name="Index.cshtml" selected="True" />
                </Node>
                <Node name="Home" expanded="True" />
                <Node name="hubs" expanded="True" />
                <Node name="Shared" expanded="True" />
              </Node>
            </Node>
          </Node>
        </State>
      </Pad>
    </Pads>
  </MonoDevelop.Ide.Workbench>
  <MonoDevelop.Ide.DebuggingService.Breakpoints>
    <BreakpointStore />
  </MonoDevelop.Ide.DebuggingService.Breakpoints>
  <MonoDevelop.Ide.DebuggingService.PinnedWatches />
  <MultiItemStartupConfigurations />
</Properties>